{
    "burstObservatory": {
        "pingConfig": {
            "timeout": "3s",
            "interval": "1m",
            "sampling": 1,
            "destination": "http://www.gstatic.com/generate_204",
            "connectivity": ""
        },
        "subjectSelector": [
            "proxy"
        ]
    },
    "dns": {
        "servers": [
            "1.1.1.1",
            "1.0.0.1"
        ],
        "queryStrategy": "UseIP"
    },
    "remarks": "🇷🇺zieng2 WL BYPASS — balanced by ilow",
    "routing": {
        "balancers": [
            {
                "tag": "Super_Balancer",
                "selector": [
                    "proxy"
                ],
                "strategy": {
                    "type": "leastLoad",
                    "settings": {
                        "maxRTT": "1s",
                        "expected": 2,
                        "baselines": [
                            "1s"
                        ],
                        "tolerance": 0.01
                    }
                },
                "fallbackTag": "direct"
            }
        ],
        "rules": [
            {
                "type": "field",
                "domain": [
                    "domain:extmaps-api.yandex.net",
                    "domain:appmetrica.yandex.ru",
                    "domain:adfstat.yandex.ru",
                    "domain:metrika.yandex.ru",
                    "domain:offerwall.yandex.net",
                    "domain:adfox.yandex.ru",
                    "domain:mc.yandex.ru",
                    "domain:analytics.google.com",
                    "domain:api.bugsnag.com",
                    "domain:app.bugsnag.com",
                    "domain:browser.sentry-cdn.com",
                    "domain:app.getsentry.com",
                    "domain:ads.vk.com",
                    "domain:ad.mail.ru",
                    "domain:top-fwz1.mail.ru",
                    "domain:ads.huawei.com",
                    "domain:adsdk.yandex.ru",
                    "domain:analytics.mobile.yandex.net"
                ],
                "outboundTag": "block"
            },
            {
                "type": "field",
                "domain": [
                    "domain:yandex.ru",
                    "domain:yandex.net",
                    "domain:yandex.com",
                    "domain:ya.ru",
                    "domain:vk.com",
                    "domain:vk.me",
                    "domain:vk-cdn.net",
                    "domain:mail.ru",
                    "domain:ok.ru",
                    "domain:gosuslugi.ru",
                    "domain:mos.ru",
                    "domain:nalog.gov.ru",
                    "domain:ozon.ru",
                    "domain:wildberries.ru",
                    "domain:avito.ru",
                    "domain:sberbank.ru",
                    "domain:sber.ru",
                    "domain:tinkoff.ru",
                    "domain:tbank.ru",
                    "domain:alfabank.ru",
                    "domain:vtb.ru",
                    "domain:gazprombank.ru",
                    "domain:rutube.ru",
                    "domain:kinopoisk.ru"
                ],
                "outboundTag": "direct"
            },
            {
                "type": "field",
                "protocol": [
                    "bittorrent"
                ],
                "outboundTag": "direct"
            },
            {
                "type": "field",
                "network": "tcp,udp",
                "balancerTag": "Super_Balancer"
            }
        ],
        "domainMatcher": "hybrid",
        "domainStrategy": "IPIfNonMatch"
    },
    "inbounds": [
        {
            "tag": "socks",
            "port": 10808,
            "listen": "127.0.0.1",
            "protocol": "socks",
            "settings": {
                "udp": true,
                "auth": "noauth"
            },
            "sniffing": {
                "enabled": true,
                "routeOnly": false,
                "destOverride": [
                    "http",
                    "tls",
                    "quic"
                ]
            }
        },
        {
            "tag": "http",
            "port": 10809,
            "listen": "127.0.0.1",
            "protocol": "http",
            "settings": {
                "allowTransparent": false
            },
            "sniffing": {
                "enabled": true,
                "routeOnly": false,
                "destOverride": [
                    "http",
                    "tls",
                    "quic"
                ]
            }
        }
    ],
    "outbounds": [
        {
            "tag": "proxy-0",
            "protocol": "vless",
            "settings": {
                "vnext": [
                    {
                        "address": "5.188.140.160",
                        "port": 5443,
                        "users": [
                            {
                                "encryption": "none",
                                "id": "1e06c388-d31c-420e-916a-94a990648e34",
                                "level": 8,
                                "security": "auto",
                                "flow": "xtls-rprx-vision"
                            }
                        ]
                    }
                ]
            },
            "streamSettings": {
                "network": "raw",
                "security": "reality",
                "realitySettings": {
                    "publicKey": "LGcG8Sqv5vPDypbaEgHV0ZGqQOBkgDepPWXyDohbVXQ",
                    "shortId": "",
                    "serverName": "max.ru",
                    "fingerprint": "firefox",
                    "show": false,
                    "spiderX": ""
                }
            },
            "mux": {
                "concurrency": -1,
                "enabled": false,
                "xudpConcurrency": 8,
                "xudpProxyUDP443": ""
            },
            "_comment": "🇷🇺 VK — #1"
        },
        {
            "tag": "proxy-1",
            "protocol": "vless",
            "settings": {
                "vnext": [
                    {
                        "address": "89.208.230.241",
                        "port": 5443,
                        "users": [
                            {
                                "encryption": "none",
                                "id": "1e06c388-d31c-420e-916a-94a990648e34",
                                "level": 8,
                                "security": "auto",
                                "flow": "xtls-rprx-vision"
                            }
                        ]
                    }
                ]
            },
            "streamSettings": {
                "network": "raw",
                "security": "reality",
                "realitySettings": {
                    "publicKey": "LGcG8Sqv5vPDypbaEgHV0ZGqQOBkgDepPWXyDohbVXQ",
                    "shortId": "",
                    "serverName": "max.ru",
                    "fingerprint": "firefox",
                    "show": false,
                    "spiderX": ""
                }
            },
            "mux": {
                "concurrency": -1,
                "enabled": false,
                "xudpConcurrency": 8,
                "xudpProxyUDP443": ""
            },
            "_comment": "🇷🇺 VK — #2"
        },
        {
            "tag": "proxy-2",
            "protocol": "vless",
            "settings": {
                "vnext": [
                    {
                        "address": "89.208.230.241",
                        "port": 5443,
                        "users": [
                            {
                                "encryption": "none",
                                "id": "1e06c388-d31c-420e-916a-94a990648e34",
                                "level": 8,
                                "security": "auto",
                                "flow": "xtls-rprx-vision"
                            }
                        ]
                    }
                ]
            },
            "streamSettings": {
                "network": "raw",
                "security": "reality",
                "realitySettings": {
                    "publicKey": "LGcG8Sqv5vPDypbaEgHV0ZGqQOBkgDepPWXyDohbVXQ",
                    "shortId": "",
                    "serverName": "max.ru",
                    "fingerprint": "chrome",
                    "show": false,
                    "spiderX": ""
                }
            },
            "mux": {
                "concurrency": -1,
                "enabled": false,
                "xudpConcurrency": 8,
                "xudpProxyUDP443": ""
            },
            "_comment": "🇷🇺 VK — #3"
        },
        {
            "tag": "proxy-3",
            "protocol": "vless",
            "settings": {
                "vnext": [
                    {
                        "address": "5.188.140.160",
                        "port": 5443,
                        "users": [
                            {
                                "encryption": "none",
                                "id": "1e06c388-d31c-420e-916a-94a990648e34",
                                "level": 8,
                                "security": "auto",
                                "flow": "xtls-rprx-vision"
                            }
                        ]
                    }
                ]
            },
            "streamSettings": {
                "network": "raw",
                "security": "reality",
                "realitySettings": {
                    "publicKey": "LGcG8Sqv5vPDypbaEgHV0ZGqQOBkgDepPWXyDohbVXQ",
                    "shortId": "",
                    "serverName": "max.ru",
                    "fingerprint": "chrome",
                    "show": false,
                    "spiderX": ""
                }
            },
            "mux": {
                "concurrency": -1,
                "enabled": false,
                "xudpConcurrency": 8,
                "xudpProxyUDP443": ""
            },
            "_comment": "🇷🇺 VK — #4"
        },
        {
            "tag": "proxy-4",
            "protocol": "vless",
            "settings": {
                "vnext": [
                    {
                        "address": "185.86.145.231",
                        "port": 5443,
                        "users": [
                            {
                                "encryption": "none",
                                "id": "1e06c388-d31c-420e-916a-94a990648e34",
                                "level": 8,
                                "security": "auto",
                                "flow": "xtls-rprx-vision"
                            }
                        ]
                    }
                ]
            },
            "streamSettings": {
                "network": "raw",
                "security": "reality",
                "realitySettings": {
                    "publicKey": "LGcG8Sqv5vPDypbaEgHV0ZGqQOBkgDepPWXyDohbVXQ",
                    "shortId": "",
                    "serverName": "max.ru",
                    "fingerprint": "chrome",
                    "show": false,
                    "spiderX": ""
                }
            },
            "mux": {
                "concurrency": -1,
                "enabled": false,
                "xudpConcurrency": 8,
                "xudpProxyUDP443": ""
            },
            "_comment": "🇷🇺 VK — #5"
        },
        {
            "tag": "proxy-5",
            "protocol": "vless",
            "settings": {
                "vnext": [
                    {
                        "address": "89.208.230.241",
                        "port": 5443,
                        "users": [
                            {
                                "encryption": "none",
                                "id": "1e06c388-d31c-420e-916a-94a990648e34",
                                "level": 8,
                                "security": "auto",
                                "flow": "xtls-rprx-vision"
                            }
                        ]
                    }
                ]
            },
            "streamSettings": {
                "network": "raw",
                "security": "reality",
                "realitySettings": {
                    "publicKey": "LGcG8Sqv5vPDypbaEgHV0ZGqQOBkgDepPWXyDohbVXQ",
                    "shortId": "",
                    "serverName": "max.ru",
                    "fingerprint": "qq",
                    "show": false,
                    "spiderX": ""
                }
            },
            "mux": {
                "concurrency": -1,
                "enabled": false,
                "xudpConcurrency": 8,
                "xudpProxyUDP443": ""
            },
            "_comment": "🇷🇺 VK — #6"
        },
        {
            "tag": "proxy-6",
            "protocol": "vless",
            "settings": {
                "vnext": [
                    {
                        "address": "89.208.230.241",
                        "port": 5443,
                        "users": [
                            {
                                "encryption": "none",
                                "id": "1e06c388-d31c-420e-916a-94a990648e34",
                                "level": 8,
                                "security": "auto",
                                "flow": "xtls-rprx-vision"
                            }
                        ]
                    }
                ]
            },
            "streamSettings": {
                "network": "raw",
                "security": "reality",
                "realitySettings": {
                    "publicKey": "LGcG8Sqv5vPDypbaEgHV0ZGqQOBkgDepPWXyDohbVXQ",
                    "shortId": "",
                    "serverName": "max.ru",
                    "fingerprint": "safari",
                    "show": false,
                    "spiderX": ""
                }
            },
            "mux": {
                "concurrency": -1,
                "enabled": false,
                "xudpConcurrency": 8,
                "xudpProxyUDP443": ""
            },
            "_comment": "🇷🇺 VK — #7"
        },
        {
            "tag": "proxy-7",
            "protocol": "vless",
            "settings": {
                "vnext": [
                    {
                        "address": "185.86.145.231",
                        "port": 5443,
                        "users": [
                            {
                                "encryption": "none",
                                "id": "1e06c388-d31c-420e-916a-94a990648e34",
                                "level": 8,
                                "security": "auto",
                                "flow": "xtls-rprx-vision"
                            }
                        ]
                    }
                ]
            },
            "streamSettings": {
                "network": "raw",
                "security": "reality",
                "realitySettings": {
                    "publicKey": "LGcG8Sqv5vPDypbaEgHV0ZGqQOBkgDepPWXyDohbVXQ",
                    "shortId": "",
                    "serverName": "max.ru",
                    "fingerprint": "firefox",
                    "show": false,
                    "spiderX": ""
                }
            },
            "mux": {
                "concurrency": -1,
                "enabled": false,
                "xudpConcurrency": 8,
                "xudpProxyUDP443": ""
            },
            "_comment": "🇷🇺 VK — #8"
        },
        {
            "tag": "proxy-8",
            "protocol": "vless",
            "settings": {
                "vnext": [
                    {
                        "address": "185.86.145.231",
                        "port": 5443,
                        "users": [
                            {
                                "encryption": "none",
                                "id": "1e06c388-d31c-420e-916a-94a990648e34",
                                "level": 8,
                                "security": "auto",
                                "flow": "xtls-rprx-vision"
                            }
                        ]
                    }
                ]
            },
            "streamSettings": {
                "network": "raw",
                "security": "reality",
                "realitySettings": {
                    "publicKey": "LGcG8Sqv5vPDypbaEgHV0ZGqQOBkgDepPWXyDohbVXQ",
                    "shortId": "",
                    "serverName": "max.ru",
                    "fingerprint": "qq",
                    "show": false,
                    "spiderX": ""
                }
            },
            "mux": {
                "concurrency": -1,
                "enabled": false,
                "xudpConcurrency": 8,
                "xudpProxyUDP443": ""
            },
            "_comment": "🇷🇺 VK — #9"
        },
        {
            "tag": "proxy-9",
            "protocol": "vless",
            "settings": {
                "vnext": [
                    {
                        "address": "185.86.145.231",
                        "port": 5443,
                        "users": [
                            {
                                "encryption": "none",
                                "id": "1e06c388-d31c-420e-916a-94a990648e34",
                                "level": 8,
                                "security": "auto",
                                "flow": "xtls-rprx-vision"
                            }
                        ]
                    }
                ]
            },
            "streamSettings": {
                "network": "raw",
                "security": "reality",
                "realitySettings": {
                    "publicKey": "LGcG8Sqv5vPDypbaEgHV0ZGqQOBkgDepPWXyDohbVXQ",
                    "shortId": "",
                    "serverName": "max.ru",
                    "fingerprint": "safari",
                    "show": false,
                    "spiderX": ""
                }
            },
            "mux": {
                "concurrency": -1,
                "enabled": false,
                "xudpConcurrency": 8,
                "xudpProxyUDP443": ""
            },
            "_comment": "🇷🇺 VK — #10"
        },
        {
            "tag": "proxy-10",
            "protocol": "vless",
            "settings": {
                "vnext": [
                    {
                        "address": "5.188.140.160",
                        "port": 5443,
                        "users": [
                            {
                                "encryption": "none",
                                "id": "1e06c388-d31c-420e-916a-94a990648e34",
                                "level": 8,
                                "security": "auto",
                                "flow": "xtls-rprx-vision"
                            }
                        ]
                    }
                ]
            },
            "streamSettings": {
                "network": "raw",
                "security": "reality",
                "realitySettings": {
                    "publicKey": "LGcG8Sqv5vPDypbaEgHV0ZGqQOBkgDepPWXyDohbVXQ",
                    "shortId": "",
                    "serverName": "max.ru",
                    "fingerprint": "qq",
                    "show": false,
                    "spiderX": ""
                }
            },
            "mux": {
                "concurrency": -1,
                "enabled": false,
                "xudpConcurrency": 8,
                "xudpProxyUDP443": ""
            },
            "_comment": "🇷🇺 VK — #11"
        },
        {
            "tag": "proxy-11",
            "protocol": "vless",
            "settings": {
                "vnext": [
                    {
                        "address": "5.188.140.160",
                        "port": 5443,
                        "users": [
                            {
                                "encryption": "none",
                                "id": "1e06c388-d31c-420e-916a-94a990648e34",
                                "level": 8,
                                "security": "auto",
                                "flow": "xtls-rprx-vision"
                            }
                        ]
                    }
                ]
            },
            "streamSettings": {
                "network": "raw",
                "security": "reality",
                "realitySettings": {
                    "publicKey": "LGcG8Sqv5vPDypbaEgHV0ZGqQOBkgDepPWXyDohbVXQ",
                    "shortId": "",
                    "serverName": "max.ru",
                    "fingerprint": "safari",
                    "show": false,
                    "spiderX": ""
                }
            },
            "mux": {
                "concurrency": -1,
                "enabled": false,
                "xudpConcurrency": 8,
                "xudpProxyUDP443": ""
            },
            "_comment": "🇷🇺 VK — #12"
        },
        {
            "tag": "proxy-12",
            "protocol": "vless",
            "settings": {
                "vnext": [
                    {
                        "address": "89.208.231.191",
                        "port": 8443,
                        "users": [
                            {
                                "encryption": "none",
                                "id": "f0dbced5-24f0-07d0-a086-64b02956e524",
                                "level": 8,
                                "security": "auto",
                                "flow": "xtls-rprx-vision"
                            }
                        ]
                    }
                ]
            },
            "streamSettings": {
                "network": "raw",
                "security": "reality",
                "realitySettings": {
                    "publicKey": "4CH3o5zOMcFNMbnwXnkAg0FFepmsc0QzhahXkUzb1ik",
                    "shortId": "d8c6b58bcbb0c323",
                    "serverName": "max.ru",
                    "fingerprint": "qq",
                    "show": false,
                    "spiderX": ""
                }
            },
            "mux": {
                "concurrency": -1,
                "enabled": false,
                "xudpConcurrency": 8,
                "xudpProxyUDP443": ""
            },
            "_comment": "🇷🇺 VK — #13"
        },
        {
            "tag": "proxy-13",
            "protocol": "vless",
            "settings": {
                "vnext": [
                    {
                        "address": "158.160.198.58",
                        "port": 443,
                        "users": [
                            {
                                "encryption": "mlkem768x25519plus.random.0rtt.QTfJnUbk6kpgCG8PVYGWL0dKYXVEm4Oax8_cqtmCjk0",
                                "id": "596b215c-3743-4893-b24a-4e396c4ab80f",
                                "level": 8,
                                "security": "auto"
                            }
                        ]
                    }
                ]
            },
            "streamSettings": {
                "network": "raw",
                "security": "reality",
                "realitySettings": {
                    "publicKey": "DQW3GuEvmRgUQnnKdHjSZhgaEDcu_07Ijuqibd72-0I",
                    "shortId": "ca7dd27a72c7c203",
                    "serverName": "api-maps.yandex.ru",
                    "fingerprint": "qq",
                    "show": false,
                    "spiderX": ""
                }
            },
            "mux": {
                "concurrency": -1,
                "enabled": false,
                "xudpConcurrency": 8,
                "xudpProxyUDP443": ""
            },
            "_comment": "🇷🇺 Yandex — #14"
        },
        {
            "tag": "proxy-14",
            "protocol": "vless",
            "settings": {
                "vnext": [
                    {
                        "address": "158.160.198.58",
                        "port": 443,
                        "users": [
                            {
                                "encryption": "mlkem768x25519plus.random.0rtt.QTfJnUbk6kpgCG8PVYGWL0dKYXVEm4Oax8_cqtmCjk0",
                                "id": "596b215c-3743-4893-b24a-4e396c4ab80f",
                                "level": 8,
                                "security": "auto"
                            }
                        ]
                    }
                ]
            },
            "streamSettings": {
                "network": "raw",
                "security": "reality",
                "realitySettings": {
                    "publicKey": "DQW3GuEvmRgUQnnKdHjSZhgaEDcu_07Ijuqibd72-0I",
                    "shortId": "ca7dd27a72c7c203",
                    "serverName": "api-maps.yandex.ru",
                    "fingerprint": "firefox",
                    "show": false,
                    "spiderX": ""
                }
            },
            "mux": {
                "concurrency": -1,
                "enabled": false,
                "xudpConcurrency": 8,
                "xudpProxyUDP443": ""
            },
            "_comment": "🇷🇺 Yandex — #15"
        },
        {
            "tag": "proxy-15",
            "protocol": "vless",
            "settings": {
                "vnext": [
                    {
                        "address": "51.250.0.174",
                        "port": 443,
                        "users": [
                            {
                                "encryption": "none",
                                "id": "852c0aa2-9997-49aa-b5aa-dacf4331884f",
                                "level": 8,
                                "security": "auto",
                                "flow": "xtls-rprx-vision"
                            }
                        ]
                    }
                ]
            },
            "streamSettings": {
                "network": "raw",
                "security": "reality",
                "realitySettings": {
                    "publicKey": "SbVKOEMjK0sIlbwg4akyBg5mL5KZwwB-ed4eEE7YnRc",
                    "shortId": "",
                    "serverName": "ads.x5.ru",
                    "fingerprint": "firefox",
                    "show": false,
                    "spiderX": ""
                }
            },
            "mux": {
                "concurrency": -1,
                "enabled": false,
                "xudpConcurrency": 8,
                "xudpProxyUDP443": ""
            },
            "_comment": "🇷🇺 Yandex — #16"
        },
        {
            "tag": "proxy-16",
            "protocol": "vless",
            "settings": {
                "vnext": [
                    {
                        "address": "51.250.0.174",
                        "port": 443,
                        "users": [
                            {
                                "encryption": "none",
                                "id": "b211bd93-c664-494b-a4e0-5b2ff26e90c4",
                                "level": 8,
                                "security": "auto",
                                "flow": "xtls-rprx-vision"
                            }
                        ]
                    }
                ]
            },
            "streamSettings": {
                "network": "raw",
                "security": "reality",
                "realitySettings": {
                    "publicKey": "SbVKOEMjK0sIlbwg4akyBg5mL5KZwwB-ed4eEE7YnRc",
                    "shortId": "",
                    "serverName": "5post-gate.x5.ru",
                    "fingerprint": "firefox",
                    "show": false,
                    "spiderX": ""
                }
            },
            "mux": {
                "concurrency": -1,
                "enabled": false,
                "xudpConcurrency": 8,
                "xudpProxyUDP443": ""
            },
            "_comment": "🇷🇺 Yandex — #17"
        },
        {
            "tag": "proxy-17",
            "protocol": "vless",
            "settings": {
                "vnext": [
                    {
                        "address": "51.250.0.174",
                        "port": 443,
                        "users": [
                            {
                                "encryption": "none",
                                "id": "21453ee3-0bd0-48de-92a8-25e573e596af",
                                "level": 8,
                                "security": "auto",
                                "flow": "xtls-rprx-vision"
                            }
                        ]
                    }
                ]
            },
            "streamSettings": {
                "network": "raw",
                "security": "reality",
                "realitySettings": {
                    "publicKey": "SbVKOEMjK0sIlbwg4akyBg5mL5KZwwB-ed4eEE7YnRc",
                    "shortId": "",
                    "serverName": "5post-gate.x5.ru",
                    "fingerprint": "qq",
                    "show": false,
                    "spiderX": ""
                }
            },
            "mux": {
                "concurrency": -1,
                "enabled": false,
                "xudpConcurrency": 8,
                "xudpProxyUDP443": ""
            },
            "_comment": "🇷🇺 Yandex — #18"
        },
        {
            "tag": "proxy-18",
            "protocol": "vless",
            "settings": {
                "vnext": [
                    {
                        "address": "51.250.0.174",
                        "port": 443,
                        "users": [
                            {
                                "encryption": "none",
                                "id": "fcacc6b7-ce97-4a0b-9332-2769ee49c858",
                                "level": 8,
                                "security": "auto",
                                "flow": "xtls-rprx-vision"
                            }
                        ]
                    }
                ]
            },
            "streamSettings": {
                "network": "raw",
                "security": "reality",
                "realitySettings": {
                    "publicKey": "SbVKOEMjK0sIlbwg4akyBg5mL5KZwwB-ed4eEE7YnRc",
                    "shortId": "",
                    "serverName": "ads.x5.ru",
                    "fingerprint": "firefox",
                    "show": false,
                    "spiderX": ""
                }
            },
            "mux": {
                "concurrency": -1,
                "enabled": false,
                "xudpConcurrency": 8,
                "xudpProxyUDP443": ""
            },
            "_comment": "🇷🇺 Yandex — #19"
        },
        {
            "tag": "proxy-19",
            "protocol": "vless",
            "settings": {
                "vnext": [
                    {
                        "address": "51.250.0.174",
                        "port": 443,
                        "users": [
                            {
                                "encryption": "none",
                                "id": "21453ee3-0bd0-48de-92a8-25e573e596af",
                                "level": 8,
                                "security": "auto",
                                "flow": "xtls-rprx-vision"
                            }
                        ]
                    }
                ]
            },
            "streamSettings": {
                "network": "raw",
                "security": "reality",
                "realitySettings": {
                    "publicKey": "SbVKOEMjK0sIlbwg4akyBg5mL5KZwwB-ed4eEE7YnRc",
                    "shortId": "",
                    "serverName": "5post-gate.x5.ru",
                    "fingerprint": "safari",
                    "show": false,
                    "spiderX": ""
                }
            },
            "mux": {
                "concurrency": -1,
                "enabled": false,
                "xudpConcurrency": 8,
                "xudpProxyUDP443": ""
            },
            "_comment": "🇷🇺 Yandex — #20"
        },
        {
            "tag": "proxy-20",
            "protocol": "vless",
            "settings": {
                "vnext": [
                    {
                        "address": "158.160.198.58",
                        "port": 443,
                        "users": [
                            {
                                "encryption": "mlkem768x25519plus.random.0rtt.QTfJnUbk6kpgCG8PVYGWL0dKYXVEm4Oax8_cqtmCjk0",
                                "id": "596b215c-3743-4893-b24a-4e396c4ab80f",
                                "level": 8,
                                "security": "auto"
                            }
                        ]
                    }
                ]
            },
            "streamSettings": {
                "network": "raw",
                "security": "reality",
                "realitySettings": {
                    "publicKey": "DQW3GuEvmRgUQnnKdHjSZhgaEDcu_07Ijuqibd72-0I",
                    "shortId": "ca7dd27a72c7c203",
                    "serverName": "api-maps.yandex.ru",
                    "fingerprint": "chrome",
                    "show": false,
                    "spiderX": ""
                }
            },
            "mux": {
                "concurrency": -1,
                "enabled": false,
                "xudpConcurrency": 8,
                "xudpProxyUDP443": ""
            },
            "_comment": "🇷🇺 Yandex — #21"
        },
        {
            "tag": "proxy-21",
            "protocol": "vless",
            "settings": {
                "vnext": [
                    {
                        "address": "158.160.198.58",
                        "port": 443,
                        "users": [
                            {
                                "encryption": "mlkem768x25519plus.random.0rtt.QTfJnUbk6kpgCG8PVYGWL0dKYXVEm4Oax8_cqtmCjk0",
                                "id": "596b215c-3743-4893-b24a-4e396c4ab80f",
                                "level": 8,
                                "security": "auto"
                            }
                        ]
                    }
                ]
            },
            "streamSettings": {
                "network": "raw",
                "security": "reality",
                "realitySettings": {
                    "publicKey": "DQW3GuEvmRgUQnnKdHjSZhgaEDcu_07Ijuqibd72-0I",
                    "shortId": "ca7dd27a72c7c203",
                    "serverName": "api-maps.yandex.ru",
                    "fingerprint": "chrome",
                    "show": false,
                    "spiderX": ""
                }
            },
            "mux": {
                "concurrency": -1,
                "enabled": false,
                "xudpConcurrency": 8,
                "xudpProxyUDP443": ""
            },
            "_comment": "🇷🇺 Yandex — #22"
        },
        {
            "tag": "proxy-22",
            "protocol": "vless",
            "settings": {
                "vnext": [
                    {
                        "address": "51.250.0.174",
                        "port": 443,
                        "users": [
                            {
                                "encryption": "none",
                                "id": "5d5d4d37-1c36-43a5-8270-f19f7e815d74",
                                "level": 8,
                                "security": "auto",
                                "flow": "xtls-rprx-vision"
                            }
                        ]
                    }
                ]
            },
            "streamSettings": {
                "network": "raw",
                "security": "reality",
                "realitySettings": {
                    "publicKey": "SbVKOEMjK0sIlbwg4akyBg5mL5KZwwB-ed4eEE7YnRc",
                    "shortId": "",
                    "serverName": "5post-gate.x5.ru",
                    "fingerprint": "firefox",
                    "show": false,
                    "spiderX": ""
                }
            },
            "mux": {
                "concurrency": -1,
                "enabled": false,
                "xudpConcurrency": 8,
                "xudpProxyUDP443": ""
            },
            "_comment": "🇷🇺 Yandex — #23"
        },
        {
            "tag": "proxy-23",
            "protocol": "vless",
            "settings": {
                "vnext": [
                    {
                        "address": "51.250.0.174",
                        "port": 443,
                        "users": [
                            {
                                "encryption": "none",
                                "id": "7fafc3f5-8153-4249-a6db-bf70c7a7fdcd",
                                "level": 8,
                                "security": "auto",
                                "flow": "xtls-rprx-vision"
                            }
                        ]
                    }
                ]
            },
            "streamSettings": {
                "network": "raw",
                "security": "reality",
                "realitySettings": {
                    "publicKey": "SbVKOEMjK0sIlbwg4akyBg5mL5KZwwB-ed4eEE7YnRc",
                    "shortId": "",
                    "serverName": "5post-gate.x5.ru",
                    "fingerprint": "qq",
                    "show": false,
                    "spiderX": ""
                }
            },
            "mux": {
                "concurrency": -1,
                "enabled": false,
                "xudpConcurrency": 8,
                "xudpProxyUDP443": ""
            },
            "_comment": "🇷🇺 Yandex — #24"
        },
        {
            "tag": "proxy-24",
            "protocol": "vless",
            "settings": {
                "vnext": [
                    {
                        "address": "51.250.0.174",
                        "port": 443,
                        "users": [
                            {
                                "encryption": "none",
                                "id": "4d317d7e-382e-4421-9c76-3aa11454f1ec",
                                "level": 8,
                                "security": "auto",
                                "flow": "xtls-rprx-vision"
                            }
                        ]
                    }
                ]
            },
            "streamSettings": {
                "network": "raw",
                "security": "reality",
                "realitySettings": {
                    "publicKey": "SbVKOEMjK0sIlbwg4akyBg5mL5KZwwB-ed4eEE7YnRc",
                    "shortId": "",
                    "serverName": "ads.x5.ru",
                    "fingerprint": "firefox",
                    "show": false,
                    "spiderX": ""
                }
            },
            "mux": {
                "concurrency": -1,
                "enabled": false,
                "xudpConcurrency": 8,
                "xudpProxyUDP443": ""
            },
            "_comment": "🇷🇺 Yandex — #25"
        },
        {
            "tag": "proxy-25",
            "protocol": "vless",
            "settings": {
                "vnext": [
                    {
                        "address": "51.250.0.174",
                        "port": 443,
                        "users": [
                            {
                                "encryption": "none",
                                "id": "3e35e41e-c633-41c2-a623-72de78653f11",
                                "level": 8,
                                "security": "auto",
                                "flow": "xtls-rprx-vision"
                            }
                        ]
                    }
                ]
            },
            "streamSettings": {
                "network": "raw",
                "security": "reality",
                "realitySettings": {
                    "publicKey": "SbVKOEMjK0sIlbwg4akyBg5mL5KZwwB-ed4eEE7YnRc",
                    "shortId": "",
                    "serverName": "5post-gate.x5.ru",
                    "fingerprint": "qq",
                    "show": false,
                    "spiderX": ""
                }
            },
            "mux": {
                "concurrency": -1,
                "enabled": false,
                "xudpConcurrency": 8,
                "xudpProxyUDP443": ""
            },
            "_comment": "🇷🇺 Yandex — #26"
        },
        {
            "tag": "proxy-26",
            "protocol": "vless",
            "settings": {
                "vnext": [
                    {
                        "address": "51.250.0.174",
                        "port": 443,
                        "users": [
                            {
                                "encryption": "none",
                                "id": "28872fb0-ced2-4b6b-a7e0-93290458aafb",
                                "level": 8,
                                "security": "auto",
                                "flow": "xtls-rprx-vision"
                            }
                        ]
                    }
                ]
            },
            "streamSettings": {
                "network": "raw",
                "security": "reality",
                "realitySettings": {
                    "publicKey": "SbVKOEMjK0sIlbwg4akyBg5mL5KZwwB-ed4eEE7YnRc",
                    "shortId": "",
                    "serverName": "ads.x5.ru",
                    "fingerprint": "qq",
                    "show": false,
                    "spiderX": ""
                }
            },
            "mux": {
                "concurrency": -1,
                "enabled": false,
                "xudpConcurrency": 8,
                "xudpProxyUDP443": ""
            },
            "_comment": "🇷🇺 Yandex — #27"
        },
        {
            "tag": "proxy-27",
            "protocol": "vless",
            "settings": {
                "vnext": [
                    {
                        "address": "51.250.0.174",
                        "port": 443,
                        "users": [
                            {
                                "encryption": "none",
                                "id": "d5f45777-e700-4a84-a943-f843776a7a52",
                                "level": 8,
                                "security": "auto",
                                "flow": "xtls-rprx-vision"
                            }
                        ]
                    }
                ]
            },
            "streamSettings": {
                "network": "raw",
                "security": "reality",
                "realitySettings": {
                    "publicKey": "SbVKOEMjK0sIlbwg4akyBg5mL5KZwwB-ed4eEE7YnRc",
                    "shortId": "",
                    "serverName": "5post-gate.x5.ru",
                    "fingerprint": "qq",
                    "show": false,
                    "spiderX": ""
                }
            },
            "mux": {
                "concurrency": -1,
                "enabled": false,
                "xudpConcurrency": 8,
                "xudpProxyUDP443": ""
            },
            "_comment": "🇷🇺 Yandex — #28"
        },
        {
            "tag": "proxy-28",
            "protocol": "vless",
            "settings": {
                "vnext": [
                    {
                        "address": "51.250.0.174",
                        "port": 443,
                        "users": [
                            {
                                "encryption": "none",
                                "id": "21453ee3-0bd0-48de-92a8-25e573e596af",
                                "level": 8,
                                "security": "auto",
                                "flow": "xtls-rprx-vision"
                            }
                        ]
                    }
                ]
            },
            "streamSettings": {
                "network": "raw",
                "security": "reality",
                "realitySettings": {
                    "publicKey": "SbVKOEMjK0sIlbwg4akyBg5mL5KZwwB-ed4eEE7YnRc",
                    "shortId": "",
                    "serverName": "5post-gate.x5.ru",
                    "fingerprint": "chrome",
                    "show": false,
                    "spiderX": ""
                }
            },
            "mux": {
                "concurrency": -1,
                "enabled": false,
                "xudpConcurrency": 8,
                "xudpProxyUDP443": ""
            },
            "_comment": "🇷🇺 Yandex — #29"
        },
        {
            "tag": "proxy-29",
            "protocol": "vless",
            "settings": {
                "vnext": [
                    {
                        "address": "51.250.0.174",
                        "port": 443,
                        "users": [
                            {
                                "encryption": "none",
                                "id": "9c062ec8-93aa-4fce-bb08-822f7e847633",
                                "level": 8,
                                "security": "auto",
                                "flow": "xtls-rprx-vision"
                            }
                        ]
                    }
                ]
            },
            "streamSettings": {
                "network": "raw",
                "security": "reality",
                "realitySettings": {
                    "publicKey": "SbVKOEMjK0sIlbwg4akyBg5mL5KZwwB-ed4eEE7YnRc",
                    "shortId": "",
                    "serverName": "ads.x5.ru",
                    "fingerprint": "chrome",
                    "show": false,
                    "spiderX": ""
                }
            },
            "mux": {
                "concurrency": -1,
                "enabled": false,
                "xudpConcurrency": 8,
                "xudpProxyUDP443": ""
            },
            "_comment": "🇷🇺 Yandex — #30"
        },
        {
            "tag": "proxy-30",
            "protocol": "vless",
            "settings": {
                "vnext": [
                    {
                        "address": "51.250.0.174",
                        "port": 443,
                        "users": [
                            {
                                "encryption": "none",
                                "id": "d71a2a0a-8699-469b-8c6a-651b399fbe0f",
                                "level": 8,
                                "security": "auto",
                                "flow": "xtls-rprx-vision"
                            }
                        ]
                    }
                ]
            },
            "streamSettings": {
                "network": "raw",
                "security": "reality",
                "realitySettings": {
                    "publicKey": "SbVKOEMjK0sIlbwg4akyBg5mL5KZwwB-ed4eEE7YnRc",
                    "shortId": "",
                    "serverName": "5post-gate.x5.ru",
                    "fingerprint": "chrome",
                    "show": false,
                    "spiderX": ""
                }
            },
            "mux": {
                "concurrency": -1,
                "enabled": false,
                "xudpConcurrency": 8,
                "xudpProxyUDP443": ""
            },
            "_comment": "🇷🇺 Yandex — #31"
        },
        {
            "tag": "proxy-31",
            "protocol": "vless",
            "settings": {
                "vnext": [
                    {
                        "address": "51.250.0.174",
                        "port": 443,
                        "users": [
                            {
                                "encryption": "none",
                                "id": "f0bd68f6-d228-4826-b483-60f1fa221571",
                                "level": 8,
                                "security": "auto",
                                "flow": "xtls-rprx-vision"
                            }
                        ]
                    }
                ]
            },
            "streamSettings": {
                "network": "raw",
                "security": "reality",
                "realitySettings": {
                    "publicKey": "SbVKOEMjK0sIlbwg4akyBg5mL5KZwwB-ed4eEE7YnRc",
                    "shortId": "",
                    "serverName": "5post-gate.x5.ru",
                    "fingerprint": "chrome",
                    "show": false,
                    "spiderX": ""
                }
            },
            "mux": {
                "concurrency": -1,
                "enabled": false,
                "xudpConcurrency": 8,
                "xudpProxyUDP443": ""
            },
            "_comment": "🇷🇺 Yandex — #32"
        },
        {
            "tag": "proxy-32",
            "protocol": "vless",
            "settings": {
                "vnext": [
                    {
                        "address": "51.250.0.174",
                        "port": 443,
                        "users": [
                            {
                                "encryption": "none",
                                "id": "9b3c4472-a53c-4e91-a13b-987dc1bdfd29",
                                "level": 8,
                                "security": "auto",
                                "flow": "xtls-rprx-vision"
                            }
                        ]
                    }
                ]
            },
            "streamSettings": {
                "network": "raw",
                "security": "reality",
                "realitySettings": {
                    "publicKey": "SbVKOEMjK0sIlbwg4akyBg5mL5KZwwB-ed4eEE7YnRc",
                    "shortId": "",
                    "serverName": "5post-gate.x5.ru",
                    "fingerprint": "chrome",
                    "show": false,
                    "spiderX": ""
                }
            },
            "mux": {
                "concurrency": -1,
                "enabled": false,
                "xudpConcurrency": 8,
                "xudpProxyUDP443": ""
            },
            "_comment": "🇷🇺 Yandex — #33"
        },
        {
            "tag": "proxy-33",
            "protocol": "vless",
            "settings": {
                "vnext": [
                    {
                        "address": "51.250.0.174",
                        "port": 443,
                        "users": [
                            {
                                "encryption": "none",
                                "id": "9b3c4472-a53c-4e91-a13b-987dc1bdfd29",
                                "level": 8,
                                "security": "auto",
                                "flow": "xtls-rprx-vision"
                            }
                        ]
                    }
                ]
            },
            "streamSettings": {
                "network": "raw",
                "security": "reality",
                "realitySettings": {
                    "publicKey": "SbVKOEMjK0sIlbwg4akyBg5mL5KZwwB-ed4eEE7YnRc",
                    "shortId": "",
                    "serverName": "5post-gate.x5.ru",
                    "fingerprint": "safari",
                    "show": false,
                    "spiderX": ""
                }
            },
            "mux": {
                "concurrency": -1,
                "enabled": false,
                "xudpConcurrency": 8,
                "xudpProxyUDP443": ""
            },
            "_comment": "🇷🇺 Yandex — #34"
        },
        {
            "tag": "proxy-34",
            "protocol": "vless",
            "settings": {
                "vnext": [
                    {
                        "address": "51.250.0.174",
                        "port": 443,
                        "users": [
                            {
                                "encryption": "none",
                                "id": "099b1932-b921-4e0d-8794-83b641088719",
                                "level": 8,
                                "security": "auto",
                                "flow": "xtls-rprx-vision"
                            }
                        ]
                    }
                ]
            },
            "streamSettings": {
                "network": "raw",
                "security": "reality",
                "realitySettings": {
                    "publicKey": "SbVKOEMjK0sIlbwg4akyBg5mL5KZwwB-ed4eEE7YnRc",
                    "shortId": "",
                    "serverName": "5post-gate.x5.ru",
                    "fingerprint": "safari",
                    "show": false,
                    "spiderX": ""
                }
            },
            "mux": {
                "concurrency": -1,
                "enabled": false,
                "xudpConcurrency": 8,
                "xudpProxyUDP443": ""
            },
            "_comment": "🇷🇺 Yandex — #35"
        },
        {
            "tag": "proxy-35",
            "protocol": "vless",
            "settings": {
                "vnext": [
                    {
                        "address": "51.250.0.174",
                        "port": 443,
                        "users": [
                            {
                                "encryption": "none",
                                "id": "21453ee3-0bd0-48de-92a8-25e573e596af",
                                "level": 8,
                                "security": "auto",
                                "flow": "xtls-rprx-vision"
                            }
                        ]
                    }
                ]
            },
            "streamSettings": {
                "network": "raw",
                "security": "reality",
                "realitySettings": {
                    "publicKey": "SbVKOEMjK0sIlbwg4akyBg5mL5KZwwB-ed4eEE7YnRc",
                    "shortId": "",
                    "serverName": "ads.x5.ru",
                    "fingerprint": "safari",
                    "show": false,
                    "spiderX": ""
                }
            },
            "mux": {
                "concurrency": -1,
                "enabled": false,
                "xudpConcurrency": 8,
                "xudpProxyUDP443": ""
            },
            "_comment": "🇷🇺 Yandex — #36"
        },
        {
            "tag": "proxy-36",
            "protocol": "vless",
            "settings": {
                "vnext": [
                    {
                        "address": "51.250.0.174",
                        "port": 443,
                        "users": [
                            {
                                "encryption": "none",
                                "id": "9c062ec8-93aa-4fce-bb08-822f7e847633",
                                "level": 8,
                                "security": "auto",
                                "flow": "xtls-rprx-vision"
                            }
                        ]
                    }
                ]
            },
            "streamSettings": {
                "network": "raw",
                "security": "reality",
                "realitySettings": {
                    "publicKey": "SbVKOEMjK0sIlbwg4akyBg5mL5KZwwB-ed4eEE7YnRc",
                    "shortId": "",
                    "serverName": "ads.x5.ru",
                    "fingerprint": "safari",
                    "show": false,
                    "spiderX": ""
                }
            },
            "mux": {
                "concurrency": -1,
                "enabled": false,
                "xudpConcurrency": 8,
                "xudpProxyUDP443": ""
            },
            "_comment": "🇷🇺 Yandex — #37"
        },
        {
            "tag": "proxy-37",
            "protocol": "vless",
            "settings": {
                "vnext": [
                    {
                        "address": "78.159.245.72",
                        "port": 2027,
                        "users": [
                            {
                                "encryption": "none",
                                "id": "af22dd57-fda0-422f-87b5-edb332450156",
                                "level": 8,
                                "security": "auto",
                                "flow": "xtls-rprx-vision"
                            }
                        ]
                    }
                ]
            },
            "streamSettings": {
                "network": "raw",
                "security": "reality",
                "realitySettings": {
                    "publicKey": "EApxy12MeXpqt-78odxizwcXT6hX9f8XeAcbMDVRAV0",
                    "shortId": "6ba7b8109dad11d1",
                    "serverName": "ads.x5.ru",
                    "fingerprint": "qq",
                    "show": false,
                    "spiderX": ""
                }
            },
            "mux": {
                "concurrency": -1,
                "enabled": false,
                "xudpConcurrency": 8,
                "xudpProxyUDP443": ""
            },
            "_comment": "🇷🇺 CDNvideo — #52"
        },
        {
            "tag": "proxy-38",
            "protocol": "vless",
            "settings": {
                "vnext": [
                    {
                        "address": "78.159.245.72",
                        "port": 2027,
                        "users": [
                            {
                                "encryption": "none",
                                "id": "af22dd57-fda0-422f-87b5-edb332450156",
                                "level": 8,
                                "security": "auto",
                                "flow": "xtls-rprx-vision"
                            }
                        ]
                    }
                ]
            },
            "streamSettings": {
                "network": "raw",
                "security": "reality",
                "realitySettings": {
                    "publicKey": "EApxy12MeXpqt-78odxizwcXT6hX9f8XeAcbMDVRAV0",
                    "shortId": "6ba7b8109dad11d1",
                    "serverName": "ads.x5.ru",
                    "fingerprint": "firefox",
                    "show": false,
                    "spiderX": ""
                }
            },
            "mux": {
                "concurrency": -1,
                "enabled": false,
                "xudpConcurrency": 8,
                "xudpProxyUDP443": ""
            },
            "_comment": "🇷🇺 CDNvideo — #53"
        },
        {
            "tag": "proxy-39",
            "protocol": "vless",
            "settings": {
                "vnext": [
                    {
                        "address": "5.129.243.64",
                        "port": 443,
                        "users": [
                            {
                                "encryption": "none",
                                "id": "935b4c83-6fab-469f-93ea-f7cae11d8a6e",
                                "level": 8,
                                "security": "auto",
                                "flow": "xtls-rprx-vision"
                            }
                        ]
                    }
                ]
            },
            "streamSettings": {
                "network": "raw",
                "security": "reality",
                "realitySettings": {
                    "publicKey": "UkWs8ZVCrm_MxuzW9a8wKJC3IPjwBJcaz7Rb5czATyA",
                    "shortId": "da122c35",
                    "serverName": "haharu7.xixihaha.it.com",
                    "fingerprint": "chrome",
                    "show": false,
                    "spiderX": ""
                }
            },
            "mux": {
                "concurrency": -1,
                "enabled": false,
                "xudpConcurrency": 8,
                "xudpProxyUDP443": ""
            },
            "_comment": "🇷🇺 Timeweb — #64"
        },
        {
            "tag": "proxy-40",
            "protocol": "vless",
            "settings": {
                "vnext": [
                    {
                        "address": "5.129.243.64",
                        "port": 443,
                        "users": [
                            {
                                "encryption": "none",
                                "id": "935b4c83-6fab-469f-93ea-f7cae11d8a6e",
                                "level": 8,
                                "security": "auto",
                                "flow": "xtls-rprx-vision"
                            }
                        ]
                    }
                ]
            },
            "streamSettings": {
                "network": "raw",
                "security": "reality",
                "realitySettings": {
                    "publicKey": "UkWs8ZVCrm_MxuzW9a8wKJC3IPjwBJcaz7Rb5czATyA",
                    "shortId": "da122c35",
                    "serverName": "haharu7.xixihaha.it.com",
                    "fingerprint": "firefox",
                    "show": false,
                    "spiderX": ""
                }
            },
            "mux": {
                "concurrency": -1,
                "enabled": false,
                "xudpConcurrency": 8,
                "xudpProxyUDP443": ""
            },
            "_comment": "🇷🇺 Timeweb — #65"
        },
        {
            "tag": "proxy-41",
            "protocol": "vless",
            "settings": {
                "vnext": [
                    {
                        "address": "5.129.243.64",
                        "port": 443,
                        "users": [
                            {
                                "encryption": "none",
                                "id": "935b4c83-6fab-469f-93ea-f7cae11d8a6e",
                                "level": 8,
                                "security": "auto",
                                "flow": "xtls-rprx-vision"
                            }
                        ]
                    }
                ]
            },
            "streamSettings": {
                "network": "raw",
                "security": "reality",
                "realitySettings": {
                    "publicKey": "UkWs8ZVCrm_MxuzW9a8wKJC3IPjwBJcaz7Rb5czATyA",
                    "shortId": "da122c35",
                    "serverName": "haharu7.xixihaha.it.com",
                    "fingerprint": "qq",
                    "show": false,
                    "spiderX": ""
                }
            },
            "mux": {
                "concurrency": -1,
                "enabled": false,
                "xudpConcurrency": 8,
                "xudpProxyUDP443": ""
            },
            "_comment": "🇷🇺 Timeweb — #66"
        },
        {
            "tag": "proxy-42",
            "protocol": "vless",
            "settings": {
                "vnext": [
                    {
                        "address": "85.239.54.134",
                        "port": 8443,
                        "users": [
                            {
                                "encryption": "none",
                                "id": "96423879-75e7-4b83-9298-98a39888a8ba",
                                "level": 8,
                                "security": "auto",
                                "flow": "xtls-rprx-vision"
                            }
                        ]
                    }
                ]
            },
            "streamSettings": {
                "network": "raw",
                "security": "reality",
                "realitySettings": {
                    "publicKey": "lRPeETJHxWt5X_fgbQALgwNwDndk8l_GHwuBUpK_cEg",
                    "shortId": "cbf87c88b9edc929",
                    "serverName": "site.rumedia-cdn.com",
                    "fingerprint": "qq",
                    "show": false,
                    "spiderX": ""
                }
            },
            "mux": {
                "concurrency": -1,
                "enabled": false,
                "xudpConcurrency": 8,
                "xudpProxyUDP443": ""
            },
            "_comment": "🇷🇺 Timeweb — #67"
        },
        {
            "tag": "direct",
            "protocol": "freedom"
        },
        {
            "tag": "block",
            "protocol": "blackhole"
        }
    ]
}